ruck/__init__.py
ruck/_history.py
ruck/_member.py
ruck/_module.py
ruck/_train.py
ruck/external/__init__.py
ruck/external/_numba.py
ruck/external/deap.py
ruck/external/ray.py
ruck/functional/__init__.py
ruck/functional/_algorithm.py
ruck/functional/_mate.py
ruck/functional/_mutate.py
ruck/functional/_select.py
ruck/functional/_select_nsga.py
ruck/util/__init__.py
ruck/util/_args.py
ruck/util/_array.py
ruck/util/_iter.py
ruck/util/_population.py
ruck/util/_timer.py
ruck-0.2.4.dist-info/LICENSE
ruck-0.2.4.dist-info/METADATA
ruck-0.2.4.dist-info/WHEEL
ruck-0.2.4.dist-info/top_level.txt
ruck-0.2.4.dist-info/RECORD
