Metadata-Version: 2.1
Name: ruck
Version: 0.2.4
Summary: Performant evolutionary algorithms for Python.
Home-page: https://github.com/nmichlo/ruck
Author: Nathan Juraj Michlo
Author-email: NathanJMichlo@gmail.com
License: UNKNOWN
Platform: UNKNOWN
Classifier: License :: OSI Approved :: MIT License
Classifier: Operating System :: OS Independent
Classifier: Programming Language :: Python :: 3.6
Classifier: Programming Language :: Python :: 3.7
Classifier: Programming Language :: Python :: 3.8
Classifier: Programming Language :: Python :: 3.9
Classifier: Intended Audience :: Science/Research
Requires-Python: >=3.6
License-File: LICENSE
Requires-Dist: pip (>=21.0)
Requires-Dist: numpy (>=1.19)
Requires-Dist: tqdm (>=4)
